ChrootMan/__init__.py
ChrootMan/actions.py
ChrootMan/helpers.py
ChrootMan/parsers.py
ChrootMan/files/config.yaml
ChrootMan-0.3.3.dist-info/LICENSE
ChrootMan-0.3.3.dist-info/METADATA
ChrootMan-0.3.3.dist-info/WHEEL
ChrootMan-0.3.3.dist-info/entry_points.txt
ChrootMan-0.3.3.dist-info/top_level.txt
ChrootMan-0.3.3.dist-info/RECORD
